kinectmatics/__init__.py
kinectmatics/libvid.py
kinectmatics/opticalflow.py
kinectmatics/timesegmentation.py
kinectmatics/version.py
kinectmatics-0.1.dist-info/METADATA
kinectmatics-0.1.dist-info/RECORD
kinectmatics-0.1.dist-info/WHEEL
kinectmatics-0.1.dist-info/top_level.txt
